Metadata-Version: 2.1
Name: proteinnpt
Version: 1.5.5
Summary: ProteinNPT: Improving Protein Property Prediction and Design with Non-Parametric Transformers
Home-page: https://github.com/OATML-Markslab/ProteinNPT
Author: Pascal Notin and Ruben Weitzman
License: MIT
License-File: LICENSE
